setup.py
src/raspberrypi_py/__init__.py
src/raspberrypi_py/components.py
src/raspberrypi_py/decorators.py
src/raspberrypi_py/low_level.py
src/raspberrypi_py.egg-info/PKG-INFO
src/raspberrypi_py.egg-info/SOURCES.txt
src/raspberrypi_py.egg-info/dependency_links.txt
src/raspberrypi_py.egg-info/not-zip-safe
src/raspberrypi_py.egg-info/requires.txt
src/raspberrypi_py.egg-info/top_level.txt