Metadata-Version: 1.0
Name: raspberrypi-py
Version: 1.0.4
Summary: RaspberryPI Python library for programming GPIO LEDs, buttons and other fun features
Home-page: https://github.com/andreipradan/raspberrypi-py
Author: Andrei Prădan
Author-email: andrei.pradan@gmail.com
License: UNKNOWN
Keywords: raspberry raspberrypi gpio raspberrypi-py leds lights
Platform: UNKNOWN
